uipath_connectors/microsoft_teams/__init__.py
uipath_connectors/microsoft_teams/client.py
uipath_connectors/microsoft_teams/errors.py
uipath_connectors/microsoft_teams/py.typed
uipath_connectors/microsoft_teams/types.py
uipath_connectors/microsoft_teams/api/__init__.py
uipath_connectors/microsoft_teams/api/bot_conversations/__init__.py
uipath_connectors/microsoft_teams/api/bot_conversations/send_message_to_channel_as_bot.py
uipath_connectors/microsoft_teams/api/curated_online_meetings/__init__.py
uipath_connectors/microsoft_teams/api/curated_online_meetings/getonline_meetings.py
uipath_connectors/microsoft_teams/api/download_recording_transcript/__init__.py
uipath_connectors/microsoft_teams/api/download_recording_transcript/download_meeting_transcript_recording.py
uipath_connectors/microsoft_teams/api/individual_chats_messages_v2/__init__.py
uipath_connectors/microsoft_teams/api/individual_chats_messages_v2/create_individual_chat_message.py
uipath_connectors/microsoft_teams/api/list_normalised_chatsmessages/__init__.py
uipath_connectors/microsoft_teams/api/list_normalised_chatsmessages/list_chat_messages.py
uipath_connectors/microsoft_teams/api/list_normalised_teamschannelsmessages/__init__.py
uipath_connectors/microsoft_teams/api/list_normalised_teamschannelsmessages/list_channel_messages.py
uipath_connectors/microsoft_teams/api/list_normalised_teamsmembers/__init__.py
uipath_connectors/microsoft_teams/api/list_normalised_teamsmembers/list_team_members.py
uipath_connectors/microsoft_teams/api/me_events/__init__.py
uipath_connectors/microsoft_teams/api/me_events/create_online_teams_meeting.py
uipath_connectors/microsoft_teams/api/me_onlinemeetings_recordings/__init__.py
uipath_connectors/microsoft_teams/api/me_onlinemeetings_recordings/list_all_recordings.py
uipath_connectors/microsoft_teams/api/me_onlinemeetings_transcripts/__init__.py
uipath_connectors/microsoft_teams/api/me_onlinemeetings_transcripts/list_all_transcripts.py
uipath_connectors_microsoft_teams-1.4.7.dev12.dist-info/METADATA
uipath_connectors_microsoft_teams-1.4.7.dev12.dist-info/WHEEL
uipath_connectors_microsoft_teams-1.4.7.dev12.dist-info/entry_points.txt
uipath_connectors_microsoft_teams-1.4.7.dev12.dist-info/top_level.txt
uipath_connectors_microsoft_teams-1.4.7.dev12.dist-info/RECORD
